[
  {
    "Class": "Łotry",
    "Name": "Złodziej",
    "Tiers": [
      {
        "Name": "Bandzior",
        "Status": "Brąz 1",
        "Attributes": [ "Initiative", "Agility", "Willpower" ],
        "Skills": [ "Atletyka", "Intuicja", "Odporność", "Opanowanie", "Broń Biała (Podstawowa)", "Język (Złodziejska Grypsera)", "Percepcja", "Skradanie (Miasto)", "Unik", "Wspinaczka" ],
        "Talents": [ "Chodu!", "Ogłuszenie", "Przestępca", "Ulicznik" ]
      },
      {
        "Name": "Gladiator",
        "Status": "Srebro 2",
        "Attributes": [ "Initiative" ],
        "Skills": [ "Tragowanie", "Intuicja", "Percepcja" ],
        "Talents": [ "Dwie Bronie", "Oburęczność" ]
      },
      {
        "Name": "Mistrz Areny",
        "Status": "Srebro 5",
        "Attributes": [ "Agility" ],
        "Skills": [ "Plotkowanie" ],
        "Talents": [ "Groźny" ]
      },
      {
        "Name": "Legenda Areny",
        "Status": "Złoto 2",
        "Attributes": [ "Fellowship" ],
        "Skills": [ "Charyzma" ],
        "Talents": [ "Straszny" ]
      }
    ]
  }
]